{
  "stage": "remap",
  "imports": [
    "import cv2 as cv"
  ],
  "function": [
    "@output_0 = cv.remap(@input_0, @input_1, @input_2, interpolation=@INTERPOLATION)"
  ],
  "configuration": [
    "@INTERPOLATION"
  ],
  "tokens": {
    "@INTERPOLATION": "Interpolation policy resolved by the same configuration used by HLS composition.",
    "@input_0": "Input image from the previous pipeline step.",
    "@input_1": "X-coordinate remap matrix provided by the concrete test configuration.",
    "@input_2": "Y-coordinate remap matrix provided by the concrete test configuration.",
    "@output_0": "Output generated by this stage."
  },
  "source": "opencv"
}
