{
  "stage": "hog_descriptor",
  "imports": [
    "from skimage.feature import hog"
  ],
  "function": [
    "@output = hog(@input, pixels_per_cell=(@K_ROWS, @K_COLS))"
  ],
  "configuration": [
    "@K_ROWS",
    "@K_COLS"
  ],
  "tokens": {
    "@K_COLS": "Composition token resolved by the functional composition layer.",
    "@K_ROWS": "Composition token resolved by the functional composition layer.",
    "@input": "Input data from the previous pipeline step.",
    "@output": "Output generated by this stage."
  },
  "source": "scikit-image"
}
